LICENSE
MANIFEST.in
README.md
VERSION
merge_pydev_pycharm.txt
pycharm-console.rst
pycharm-readme.rst
pydev_app_engine_debug_startup.py
pydevconsole.py
pydevd.py
pydevd_file_utils.py
pydevd_pycharm.py
pydevd_tracing.py
pyproject.toml
setup.py
setup_cython.py
_pydev_bundle/__init__.py
_pydev_bundle/_pydev_calltip_util.py
_pydev_bundle/_pydev_completer.py
_pydev_bundle/_pydev_filesystem_encoding.py
_pydev_bundle/_pydev_getopt.py
_pydev_bundle/_pydev_imports_tipper.py
_pydev_bundle/_pydev_jy_imports_tipper.py
_pydev_bundle/_pydev_log.py
_pydev_bundle/_pydev_tipper_common.py
_pydev_bundle/fix_getpass.py
_pydev_bundle/pydev_code_executor.py
_pydev_bundle/pydev_console_commands.py
_pydev_bundle/pydev_console_types.py
_pydev_bundle/pydev_console_utils.py
_pydev_bundle/pydev_import_hook.py
_pydev_bundle/pydev_imports.py
_pydev_bundle/pydev_ipython_code_executor.py
_pydev_bundle/pydev_ipython_completer.py
_pydev_bundle/pydev_ipython_console.py
_pydev_bundle/pydev_ipython_console_011.py
_pydev_bundle/pydev_ipython_rich_output.py
_pydev_bundle/pydev_is_thread_alive.py
_pydev_bundle/pydev_localhost.py
_pydev_bundle/pydev_log.py
_pydev_bundle/pydev_monkey.py
_pydev_bundle/pydev_monkey_qt.py
_pydev_bundle/pydev_override.py
_pydev_bundle/pydev_stdin.py
_pydev_bundle/pydev_umd.py
_pydev_bundle/pydev_versioncheck.py
_pydev_imps/__init__.py
_pydev_imps/_pydev_BaseHTTPServer.py
_pydev_imps/_pydev_SimpleXMLRPCServer.py
_pydev_imps/_pydev_SocketServer.py
_pydev_imps/_pydev_execfile.py
_pydev_imps/_pydev_pkgutil_old.py
_pydev_imps/_pydev_saved_modules.py
_pydev_imps/_pydev_sys_patch.py
_pydev_imps/_pydev_xmlrpclib.py
_pydev_runfiles/__init__.py
_pydev_runfiles/pydev_runfiles.py
_pydev_runfiles/pydev_runfiles_coverage.py
_pydev_runfiles/pydev_runfiles_nose.py
_pydev_runfiles/pydev_runfiles_parallel.py
_pydev_runfiles/pydev_runfiles_parallel_client.py
_pydev_runfiles/pydev_runfiles_pytest2.py
_pydev_runfiles/pydev_runfiles_unittest.py
_pydev_runfiles/pydev_runfiles_xml_rpc.py
pydevd_pycharm.egg-info/PKG-INFO
pydevd_pycharm.egg-info/SOURCES.txt
pydevd_pycharm.egg-info/dependency_links.txt
pydevd_pycharm.egg-info/entry_points.txt
pydevd_pycharm.egg-info/not-zip-safe
pydevd_pycharm.egg-info/top_level.txt
